empanada_napari/__init__.py
empanada_napari/_export_batch_segs.py
empanada_napari/_export_import_models.py
empanada_napari/_filter_small_labels.py
empanada_napari/_finetune.py
empanada_napari/_label_counter_widget.py
empanada_napari/_merge_split_widget.py
empanada_napari/_pick_patches.py
empanada_napari/_register_model.py
empanada_napari/_slice_inference.py
empanada_napari/_train.py
empanada_napari/_version.py
empanada_napari/_volume_inference.py
empanada_napari/finetune.py
empanada_napari/inference.py
empanada_napari/multigpu.py
empanada_napari/napari.yaml
empanada_napari/train.py
empanada_napari/utils.py
empanada_napari/configs/MitoNet_v1.yaml
empanada_napari/configs/MitoNet_v1_mini.yaml
empanada_napari/resources/empanada_logo.png
empanada_napari/training/bifpn_model.yaml
empanada_napari/training/finetune_config.yaml
empanada_napari/training/pdl_model.yaml
empanada_napari/training/train_config.yaml
cryaleconcho-0.0.7.dist-info/LICENSE
cryaleconcho-0.0.7.dist-info/METADATA
cryaleconcho-0.0.7.dist-info/WHEEL
cryaleconcho-0.0.7.dist-info/entry_points.txt
cryaleconcho-0.0.7.dist-info/top_level.txt
cryaleconcho-0.0.7.dist-info/RECORD
