Metadata-Version: 2.1
Name: cryaleconcho
Version: 0.0.7
Summary: Napari plugin of algorithms for Panoptic Segmentation of organelles in EM
Home-page: https://github.com/volume-em/empanada-napari
Author: Ryan Conrad
Author-email: conradrw@nih.gov
License: BSD-3-Clause
Project-URL: Bug Tracker, https://github.com/volume-em/empanada-napari/issues
Project-URL: Documentation, https://github.com/volume-em/empanada-napari#README.md
Project-URL: Source Code, https://github.com/volume-em/empanada-napari
Project-URL: User Support, https://github.com/volume-em/empanada-napari/issues
Classifier: Development Status :: 2 - Pre-Alpha
Classifier: Intended Audience :: Developers
Classifier: Framework :: napari
Classifier: Topic :: Software Development :: Testing
Classifier: Programming Language :: Python
Classifier: Programming Language :: Python :: 3
Classifier: Programming Language :: Python :: 3.7
Classifier: Programming Language :: Python :: 3.8
Classifier: Programming Language :: Python :: 3.9
Classifier: Operating System :: OS Independent
Classifier: License :: OSI Approved :: BSD License
Requires-Python: >=3.7
License-File: LICENSE
Requires-Dist: napari >=0.4.16
Requires-Dist: numpy ==1.22
Requires-Dist: napari-plugin-engine >=0.1.4
Requires-Dist: scikit-image >=0.19
Requires-Dist: empanada-dl >=0.1.7
Requires-Dist: imagecodecs
Requires-Dist: openpyxl
